Metadata-Version: 2.1
Name: simplelayout-yuloveyet
Version: 0.1.5
Summary: A simplelayout test for Python
Home-page: https://github.com/idrl-assignment/3-simplelayout-package-yuloveyet
Author: Yu Li
Author-email: liyu.work@outlook.com
License: UNKNOWN
Keywords: Python,test
Platform: UNKNOWN
Classifier: Development Status :: 3 - Alpha
Classifier: Programming Language :: Python :: 3.8
Requires-Python: >=3.5, <4
Requires-Dist: pytest
Requires-Dist: numpy
Requires-Dist: matplotlib
Requires-Dist: scipy
